mykernel/__init__.py
mykernel/commons.py
mykernel/locale/es/LC_MESSAGES/mykernel.mo
mykernel/locale/fr/LC_MESSAGES/mykernel.mo
mykernel/mykernel_check.py
mykernel/mykernel_compile.py
mykernel/mykernel_initramfs.py
mykernel/poethepoet.py
mykernel/reusing/cpupower.py
mykernel/reusing/file_functions.py
mykernel/reusing/github.py
mykernel/reusing/myconfigparser.py
mykernel/version.py
mykernel-1.0.0.dist-info/LICENSE.txt
mykernel-1.0.0.dist-info/METADATA
mykernel-1.0.0.dist-info/WHEEL
mykernel-1.0.0.dist-info/entry_points.txt
mykernel-1.0.0.dist-info/RECORD
