Metadata-Version: 2.3
Name: mykernel
Version: 1.0.0
Summary: My kernel scripts to compile it in Gentoo systems
License: GPL-3.0-only
Author: turulomio
Author-email: turulomio@yahoo.es
Requires-Python: >=3.12,<4.0.0
Classifier: License :: OSI Approved :: GNU General Public License v3 (GPLv3)
Classifier: Programming Language :: Python :: 3
Classifier: Programming Language :: Python :: 3.12
Classifier: Programming Language :: Python :: 3.13
Requires-Dist: colorama (>=0.4.6,<0.5.0)
Requires-Dist: pycryptodome (>=3.22.0,<4.0.0)
Requires-Dist: pydicts (>=0.17.0)
Project-URL: Homepage, https://github.com/turulomio/mykernel/
Project-URL: Repository, https://github.com/turulomio/mykernel/
Project-URL: changelog, https://github.com/turulomio/mykernel#changelog
